senseye/__init__.py
senseye/common/common_pb2.py
senseye/common/common_pb2_grpc.py
senseye/common/status_pb2.py
senseye/common/status_pb2_grpc.py
senseye/gateway/gateway_service_pb2.py
senseye/gateway/gateway_service_pb2_grpc.py
senseye_api_client/__init__.py
senseye_api_client/api.py
senseye_api_client/utils.py
senseye_api_client/video_task.py
senseye_api_client/interceptors/__init__.py
senseye_api_client/interceptors/client_interceptor_generic.py
senseye_api_client/interceptors/client_interceptor_header.py
senseye_api_client-0.2.2.dist-info/LICENSE
senseye_api_client-0.2.2.dist-info/METADATA
senseye_api_client-0.2.2.dist-info/WHEEL
senseye_api_client-0.2.2.dist-info/top_level.txt
senseye_api_client-0.2.2.dist-info/RECORD
