Metadata-Version: 2.1
Name: senseye-api-client
Version: 0.2.2
Summary: Client code for Senseye's Eucalyptus API.
Home-page: UNKNOWN
Author: Senseye Inc
License: UNKNOWN
Project-URL: Homepage, http://senseye.co/
Project-URL: Documentation, https://senseye-api-client.readthedocs.io/en/latest/
Project-URL: Source Code, https://github.com/senseyeinc/senseye-api-client
Platform: UNKNOWN
Requires-Dist: grpcio
Requires-Dist: grpcio-tools
Requires-Dist: google-api-python-client
Requires-Dist: senseye-cameras (>=v1.0.8)
Requires-Dist: pyyaml
Requires-Dist: pyjwt
Requires-Dist: requests
Requires-Dist: invoke
